auth_kit/__init__.py
auth_kit/allauth_enhanced.py
auth_kit/api_descriptions.py
auth_kit/app_settings.py
auth_kit/authentication.py
auth_kit/forms.py
auth_kit/jwt_auth.py
auth_kit/py.typed
auth_kit/serializer_fields.py
auth_kit/test_utils.py
auth_kit/urls.py
auth_kit/utils.py
auth_kit/locale/af/LC_MESSAGES/django.po
auth_kit/locale/ar/LC_MESSAGES/django.po
auth_kit/locale/az/LC_MESSAGES/django.po
auth_kit/locale/be/LC_MESSAGES/django.po
auth_kit/locale/bg/LC_MESSAGES/django.po
auth_kit/locale/bs/LC_MESSAGES/django.po
auth_kit/locale/ca/LC_MESSAGES/django.po
auth_kit/locale/cs/LC_MESSAGES/django.po
auth_kit/locale/cy/LC_MESSAGES/django.po
auth_kit/locale/da/LC_MESSAGES/django.po
auth_kit/locale/de/LC_MESSAGES/django.po
auth_kit/locale/el/LC_MESSAGES/django.po
auth_kit/locale/en/LC_MESSAGES/django.po
auth_kit/locale/es/LC_MESSAGES/django.po
auth_kit/locale/et/LC_MESSAGES/django.po
auth_kit/locale/fa/LC_MESSAGES/django.po
auth_kit/locale/fi/LC_MESSAGES/django.po
auth_kit/locale/fr/LC_MESSAGES/django.po
auth_kit/locale/gl/LC_MESSAGES/django.po
auth_kit/locale/he/LC_MESSAGES/django.po
auth_kit/locale/hi/LC_MESSAGES/django.po
auth_kit/locale/hr/LC_MESSAGES/django.po
auth_kit/locale/hu/LC_MESSAGES/django.po
auth_kit/locale/hy/LC_MESSAGES/django.po
auth_kit/locale/id/LC_MESSAGES/django.po
auth_kit/locale/is/LC_MESSAGES/django.po
auth_kit/locale/it/LC_MESSAGES/django.po
auth_kit/locale/ja/LC_MESSAGES/django.po
auth_kit/locale/kk/LC_MESSAGES/django.po
auth_kit/locale/kn/LC_MESSAGES/django.po
auth_kit/locale/ko/LC_MESSAGES/django.po
auth_kit/locale/lt/LC_MESSAGES/django.po
auth_kit/locale/lv/LC_MESSAGES/django.po
auth_kit/locale/mi/LC_MESSAGES/django.po
auth_kit/locale/mk/LC_MESSAGES/django.po
auth_kit/locale/mr/LC_MESSAGES/django.po
auth_kit/locale/ms/LC_MESSAGES/django.po
auth_kit/locale/ne/LC_MESSAGES/django.po
auth_kit/locale/nl/LC_MESSAGES/django.po
auth_kit/locale/no/LC_MESSAGES/django.po
auth_kit/locale/pl/LC_MESSAGES/django.po
auth_kit/locale/pt/LC_MESSAGES/django.po
drf_auth_kit-1.1.3.dist-info/METADATA
drf_auth_kit-1.1.3.dist-info/WHEEL
drf_auth_kit-1.1.3.dist-info/licenses/AUTHORS.rst
drf_auth_kit-1.1.3.dist-info/licenses/LICENSE
drf_auth_kit-1.1.3.dist-info/RECORD
