Metadata-Version: 2.4
Name: drf-auth-kit
Version: 1.1.3
Summary: Modern Django REST Framework authentication toolkit with JWT cookies, social login, and 2FA support
Project-URL: Documentation, https://drf-auth-kit.readthedocs.io/
Project-URL: Homepage, https://github.com/forthecraft/drf-auth-kit
Project-URL: Repository, https://github.com/forthecraft/drf-auth-kit
Author-email: Huy Nguyen <danghuy1999@gmail.com>
License: MIT License
License-File: AUTHORS.rst
License-File: LICENSE
Classifier: Environment :: Web Environment
Classifier: Intended Audience :: Developers
Classifier: Intended Audience :: Information Technology
Classifier: License :: OSI Approved :: BSD License
Classifier: Operating System :: OS Independent
Classifier: Programming Language :: Python :: 3
Classifier: Programming Language :: Python :: 3 :: Only
Classifier: Programming Language :: Python :: 3.10
Classifier: Programming Language :: Python :: 3.11
Classifier: Programming Language :: Python :: 3.12
Classifier: Programming Language :: Python :: 3.13
Classifier: Topic :: Internet :: WWW/HTTP
Classifier: Topic :: Internet :: WWW/HTTP :: Dynamic Content
Classifier: Topic :: Software Development
Classifier: Topic :: Software Development :: Libraries
Classifier: Topic :: Software Development :: Libraries :: Application Frameworks
Requires-Python: <4.0,>=3.10
Requires-Dist: django-allauth<66.0.0,>=65.5.0
Requires-Dist: django<7,>=4.2
Requires-Dist: djangorestframework-simplejwt<6,>=5
Requires-Dist: djangorestframework<4,>=3
Requires-Dist: drf-spectacular
Requires-Dist: structlog
Provides-Extra: all
Requires-Dist: django-allauth[socialaccount]>=65.5.0; extra == 'all'
Requires-Dist: pyotp>=2.9.0; extra == 'all'
Provides-Extra: mfa
Requires-Dist: pyotp>=2.9.0; extra == 'mfa'
Provides-Extra: social
Requires-Dist: django-allauth[socialaccount]>=65.5.0; extra == 'social'
